Metadata-Version: 1.0
Name: abork-config-initiator
Version: 1.1.8
Summary: Configuration File Initiator
Home-page: UNKNOWN
Author: Alex Bork
Author-email: UNKNOWN
License: UNKNOWN
Platform: UNKNOWN
